{"href":"https://kenai.com/api/projects/jruby/features/wiki/pages/Roadmap/revisions/1.json","name":"Roadmap","number":1,"page_href":"https://kenai.com/api/projects/jruby/features/wiki/pages/Roadmap.json","person":"john_brock","description":"","text":"The post-1.0 roadmap is currently being firmed up.\r\n\r\nSee the following links for thoughts on where JRuby is headed post-1.0: [http://headius.blogspot.com/2007/06/jruby-10-released.html], [http://blog.nicksieger.com/articles/2007/06/10/jruby-1-0], [http://www.artima.com/forums/flat.jsp?forum=276&thread=208264].  You can also join the [[Mailing Lists]] and participate in the discussion!\r\n\r\nThe [[Roadmap (January 2007 - June 2007)|archived 1.0 roadmap is here]].\r\n","created_at":"2008-08-11T23:59:34Z","content_type":"application/vnd.com.kenai.page.revision+json"}